{
  "ModId": "p3ppc.guaranteedItemDrops",
  "ModName": "Guaranteed Item Drops",
  "ModAuthor": "AnimatedSwine37",
  "ModVersion": "1.0.0",
  "ModDescription": "Makes enemies that drop items always do so instead of only having a random chance to.",
  "ModDll": "p3ppc.guaranteedItemDrops.dll",
  "ModIcon": "Preview.png",
  "ModR2RManagedDll32": "x86/p3ppc.guaranteedItemDrops.dll",
  "ModR2RManagedDll64": "x64/p3ppc.guaranteedItemDrops.dll",
  "ModNativeDll32": "",
  "ModNativeDll64": "",
  "IsLibrary": false,
  "ReleaseMetadataFileName": "p3ppc.guaranteedItemDrops.ReleaseMetadata.json",
  "PluginData": {},
  "IsUniversalMod": false,
  "ModDependencies": [
    "reloaded.sharedlib.hooks",
    "Reloaded.Memory.SigScan.ReloadedII"
  ],
  "OptionalDependencies": [],
  "SupportedAppId": [ "p3p.exe" ],
  "ProjectUrl": ""
}